{
    "config_id": 1113,
    "config": {
        "ID": 1113,
        "Model": "YOLOv8 Nano",
        "BoxInclusion": false,
        "MaskInclusion": true,
        "NumberOfPOIs": 3,
        "POIPlacementAlgorithm": "Voronoi",
        "PerimeterBuffer": "10%",
        "BoundingBoxDistortion": NaN,
        "MaskDistortion": "110%"
    },
    "system_info": {
        "cpu_info": {
            "platform": "Linux-5.15.0-122-generic-x86_64-with-glibc2.10",
            "processor": "x86_64",
            "cpu_count": 64
        },
        "gpu_info": {
            "count": 1,
            "devices": [
                "NVIDIA A100-SXM4-80GB"
            ]
        }
    },
    "per_image": [
        {
            "image_name": "Cu-Ni-Powder_250x_10_SE_png.rf.cd93ec4589ad8f4e412cb1ec0e805016.jpg",
            "original_image_path": "/home/sprice/ICCV25/demo.v7i.coco/test/Cu-Ni-Powder_250x_10_SE_png.rf.cd93ec4589ad8f4e412cb1ec0e805016.jpg",
            "gt_mask_path": "/home/sprice/ICCV25/demo.v7i.coco/test/annotations/Cu-Ni-Powder_250x_10_SE_png.rf.cd93ec4589ad8f4e412cb1ec0e805016_mask.png",
            "processing_time_sec": 3.4103846549987793,
            "base_box_AP@50": 1.0,
            "base_box_AP@75": 1.0,
            "base_box_AP@95": 0.29462946294629466,
            "base_box_AP@50:95": 0.7648764876487648,
            "base_mask_AP@50": 1.0,
            "base_mask_AP@75": 0.8982898289828983,
            "base_mask_AP@95": 0.031353135313531344,
            "base_mask_AP@50:95": 0.6432143214321433,
            "sam_box_AP@50": 0.2808580858085808,
            "sam_box_AP@75": 0.2808580858085808,
            "sam_box_AP@95": 0.05196186285295196,
            "sam_box_AP@50:95": 0.20455934482337118,
            "sam_mask_AP@50": 0.4098502157908098,
            "sam_mask_AP@75": 0.13155623254633156,
            "sam_mask_AP@95": 0.020077007700770075,
            "sam_mask_AP@50:95": 0.18716115201263714,
            "base_box_AR@50": 0.5,
            "base_box_AR@75": 0.5,
            "base_box_AR@95": 0.032575757575757563,
            "base_box_AR@50:95": 0.34419191919191916,
            "base_mask_AR@50": 0.5,
            "base_mask_AR@75": 0.42727272727272725,
            "base_mask_AR@95": -0.17727272727272725,
            "base_mask_AR@50:95": 0.25,
            "sam_box_AR@50": 0.032575757575757563,
            "sam_box_AR@75": 0.032575757575757563,
            "sam_box_AR@95": -0.10454545454545452,
            "sam_box_AR@50:95": -0.013131313131313133,
            "sam_mask_AR@50": 0.16969696969696968,
            "sam_mask_AR@75": -0.04015151515151516,
            "sam_mask_AR@95": -0.17727272727272725,
            "sam_mask_AR@50:95": -0.015909090909090914
        },
        {
            "image_name": "Cu-Ni-Powder_250x_1_SE_V1_png.rf.675fe4943c221bb28cfe029af5482897.jpg",
            "original_image_path": "/home/sprice/ICCV25/demo.v7i.coco/test/Cu-Ni-Powder_250x_1_SE_V1_png.rf.675fe4943c221bb28cfe029af5482897.jpg",
            "gt_mask_path": "/home/sprice/ICCV25/demo.v7i.coco/test/annotations/Cu-Ni-Powder_250x_1_SE_V1_png.rf.675fe4943c221bb28cfe029af5482897_mask.png",
            "processing_time_sec": 26.623170375823975,
            "base_box_AP@50": 0.7037569224243305,
            "base_box_AP@75": 0.46924751924956565,
            "base_box_AP@95": 0.00028438217971457006,
            "base_box_AP@50:95": 0.3910962746178702,
            "base_mask_AP@50": 0.6460043722360486,
            "base_mask_AP@75": 0.346235313093337,
            "base_mask_AP@95": 0.0,
            "base_mask_AP@50:95": 0.33074656177646183,
            "sam_box_AP@50": 0.3355222628958965,
            "sam_box_AP@75": 0.20134097967972775,
            "sam_box_AP@95": 0.09538368010229015,
            "sam_box_AP@50:95": 0.21074897422597144,
            "sam_mask_AP@50": 0.3432093399479335,
            "sam_mask_AP@75": 0.15448711834359327,
            "sam_mask_AP@95": 0.037418442305059994,
            "sam_mask_AP@50:95": 0.17837163353219557,
            "base_box_AR@50": 0.7658391955266955,
            "base_box_AR@75": 0.5839984668109668,
            "base_box_AR@95": 0.006572420634920634,
            "base_box_AR@50:95": 0.4521366943241944,
            "base_mask_AR@50": 0.7142180735930735,
            "base_mask_AR@75": 0.453226461038961,
            "base_mask_AR@95": 0.0,
            "base_mask_AR@50:95": 0.3891481782106782,
            "sam_box_AR@50": 0.44734172077922074,
            "sam_box_AR@75": 0.3038419913419913,
            "sam_box_AR@95": 0.11803300865800866,
            "sam_box_AR@50:95": 0.28973890692640686,
            "sam_mask_AR@50": 0.46870490620490624,
            "sam_mask_AR@75": 0.27454229797979796,
            "sam_mask_AR@95": 0.051621121933621936,
            "sam_mask_AR@50:95": 0.26495610870610875
        },
        {
            "image_name": "Cu-Ni-Powder_250x_6_SE_V1_png.rf.e53ddff8f68997450136adf624221578.jpg",
            "original_image_path": "/home/sprice/ICCV25/demo.v7i.coco/test/Cu-Ni-Powder_250x_6_SE_V1_png.rf.e53ddff8f68997450136adf624221578.jpg",
            "gt_mask_path": "/home/sprice/ICCV25/demo.v7i.coco/test/annotations/Cu-Ni-Powder_250x_6_SE_V1_png.rf.e53ddff8f68997450136adf624221578_mask.png",
            "processing_time_sec": 24.416009426116943,
            "base_box_AP@50": 0.7654170966730028,
            "base_box_AP@75": 0.3763174261624039,
            "base_box_AP@95": 0.0502049563930752,
            "base_box_AP@50:95": 0.39731315974282727,
            "base_mask_AP@50": 0.6999680177449493,
            "base_mask_AP@75": 0.35572399661988663,
            "base_mask_AP@95": 0.0,
            "base_mask_AP@50:95": 0.3518973381216119,
            "sam_box_AP@50": 0.26899218822869897,
            "sam_box_AP@75": 0.1321121241949617,
            "sam_box_AP@95": 0.03788123725163213,
            "sam_box_AP@50:95": 0.14632851655843093,
            "sam_mask_AP@50": 0.2016818958808994,
            "sam_mask_AP@75": 0.06063144898968554,
            "sam_mask_AP@95": 0.004991184908764433,
            "sam_mask_AP@50:95": 0.0891015099264498,
            "base_box_AR@50": 0.831736576487135,
            "base_box_AR@75": 0.5122197402167619,
            "base_box_AR@95": 0.08849176801522296,
            "base_box_AR@50:95": 0.47748269490637324,
            "base_mask_AR@50": 0.8142963514519731,
            "base_mask_AR@75": 0.4586084222718624,
            "base_mask_AR@95": 0.0,
            "base_mask_AR@50:95": 0.4243015912412786,
            "sam_box_AR@50": 0.4341689418383387,
            "sam_box_AR@75": 0.22144452717795982,
            "sam_box_AR@95": 0.12423264664515596,
            "sam_box_AR@50:95": 0.2599487052204848,
            "sam_mask_AR@50": 0.3718375113758584,
            "sam_mask_AR@75": 0.19485397534541243,
            "sam_mask_AR@95": 0.03531066435012824,
            "sam_mask_AR@50:95": 0.20066738369046633
        },
        {
            "image_name": "HP743_5S_500x_png.rf.9ff406796462449f85c2039537f32d6f.jpg",
            "original_image_path": "/home/sprice/ICCV25/demo.v7i.coco/test/HP743_5S_500x_png.rf.9ff406796462449f85c2039537f32d6f.jpg",
            "gt_mask_path": "/home/sprice/ICCV25/demo.v7i.coco/test/annotations/HP743_5S_500x_png.rf.9ff406796462449f85c2039537f32d6f_mask.png",
            "processing_time_sec": 4.57845664024353,
            "base_box_AP@50": 0.927919682724575,
            "base_box_AP@75": 0.927919682724575,
            "base_box_AP@95": 0.19426109277594428,
            "base_box_AP@50:95": 0.6833668194083647,
            "base_mask_AP@50": 0.9974762182100564,
            "base_mask_AP@75": 0.927919682724575,
            "base_mask_AP@95": 0.1078107810781078,
            "base_mask_AP@50:95": 0.677735560670913,
            "sam_box_AP@50": 0.4619528317839326,
            "sam_box_AP@75": 0.2100562997476218,
            "sam_box_AP@95": 0.16501650165016502,
            "sam_box_AP@50:95": 0.27900854439390643,
            "sam_mask_AP@50": 0.5839989461130987,
            "sam_mask_AP@75": 0.401863715783343,
            "sam_mask_AP@95": 0.2552255225522553,
            "sam_mask_AP@50:95": 0.41369606148289906,
            "base_box_AR@50": 0.453125,
            "base_box_AR@75": 0.453125,
            "base_box_AR@95": -0.0625,
            "base_box_AR@50:95": 0.28125,
            "base_mask_AR@50": 0.5,
            "base_mask_AR@75": 0.453125,
            "base_mask_AR@95": -0.15625,
            "base_mask_AR@50:95": 0.265625,
            "sam_box_AR@50": 0.171875,
            "sam_box_AR@75": -0.0625,
            "sam_box_AR@95": -0.109375,
            "sam_box_AR@50:95": 0.0,
            "sam_mask_AR@50": 0.265625,
            "sam_mask_AR@75": 0.125,
            "sam_mask_AR@95": -0.015625,
            "sam_mask_AR@50:95": 0.125
        },
        {
            "image_name": "MW_FeMnAl_500_22-11_png.rf.7095906a9fa6befd1eb267219b11b181.jpg",
            "original_image_path": "/home/sprice/ICCV25/demo.v7i.coco/test/MW_FeMnAl_500_22-11_png.rf.7095906a9fa6befd1eb267219b11b181.jpg",
            "gt_mask_path": "/home/sprice/ICCV25/demo.v7i.coco/test/annotations/MW_FeMnAl_500_22-11_png.rf.7095906a9fa6befd1eb267219b11b181_mask.png",
            "processing_time_sec": 54.44300818443298,
            "base_box_AP@50": 0.9248772866840068,
            "base_box_AP@75": 0.6419180799448849,
            "base_box_AP@95": 0.004183903215102486,
            "base_box_AP@50:95": 0.5236597566146646,
            "base_mask_AP@50": 0.8683765685731633,
            "base_mask_AP@75": 0.5881139928576941,
            "base_mask_AP@95": 0.0,
            "base_mask_AP@50:95": 0.4854968538102858,
            "sam_box_AP@50": 0.40997655985717,
            "sam_box_AP@75": 0.2023318591709396,
            "sam_box_AP@95": 0.019666823031173574,
            "sam_box_AP@50:95": 0.21065841401976107,
            "sam_mask_AP@50": 0.47383897499162064,
            "sam_mask_AP@75": 0.2436279379196504,
            "sam_mask_AP@95": 0.0330200024266819,
            "sam_mask_AP@50:95": 0.250162305112651,
            "base_box_AR@50": 0.9663795498749652,
            "base_box_AR@75": 0.736257756784292,
            "base_box_AR@95": 0.039087733922190865,
            "base_box_AR@50:95": 0.5805750135271494,
            "base_mask_AR@50": 0.9241260974052247,
            "base_mask_AR@75": 0.6756792822567672,
            "base_mask_AR@95": 0.0,
            "base_mask_AR@50:95": 0.5332684598873306,
            "sam_box_AR@50": 0.5577617808065594,
            "sam_box_AR@75": 0.34037659096337675,
            "sam_box_AR@95": 0.06254905114968583,
            "sam_box_AR@50:95": 0.32022914097320726,
            "sam_mask_AR@50": 0.6126631179226198,
            "sam_mask_AR@75": 0.374254300658565,
            "sam_mask_AR@95": 0.0705277538107564,
            "sam_mask_AR@50:95": 0.3524817241306471
        },
        {
            "image_name": "OMG_Cu_1250_07_png.rf.ff417e92b36bba2bb91175ce144ff6ab.jpg",
            "original_image_path": "/home/sprice/ICCV25/demo.v7i.coco/test/OMG_Cu_1250_07_png.rf.ff417e92b36bba2bb91175ce144ff6ab.jpg",
            "gt_mask_path": "/home/sprice/ICCV25/demo.v7i.coco/test/annotations/OMG_Cu_1250_07_png.rf.ff417e92b36bba2bb91175ce144ff6ab_mask.png",
            "processing_time_sec": 9.939322471618652,
            "base_box_AP@50": 0.8886807728391886,
            "base_box_AP@75": 0.8433883724506904,
            "base_box_AP@95": 0.1391962725684333,
            "base_box_AP@50:95": 0.6237551392861042,
            "base_mask_AP@50": 0.8669353494489235,
            "base_mask_AP@75": 0.6623512351235125,
            "base_mask_AP@95": 0.010726072607260726,
            "base_mask_AP@50:95": 0.5133375523932322,
            "sam_box_AP@50": 0.2924792479247925,
            "sam_box_AP@75": 0.03620838274303621,
            "sam_box_AP@95": 0.0143014301430143,
            "sam_box_AP@50:95": 0.11432968693694767,
            "sam_mask_AP@50": 0.3537905964509494,
            "sam_mask_AP@75": 0.04128031850804128,
            "sam_mask_AP@95": 0.0,
            "sam_mask_AP@50:95": 0.13169030498633025,
            "base_box_AR@50": 0.46886446886446886,
            "base_box_AR@75": 0.43772893772893773,
            "base_box_AR@95": -0.12545787545787546,
            "base_box_AR@50:95": 0.26037851037851034,
            "base_mask_AR@50": 0.46886446886446886,
            "base_mask_AR@75": 0.2891483516483516,
            "base_mask_AR@95": -0.21886446886446886,
            "base_mask_AR@50:95": 0.17971611721611722,
            "sam_box_AR@50": 0.06135531135531136,
            "sam_box_AR@75": -0.0943223443223443,
            "sam_box_AR@95": -0.18772893772893773,
            "sam_box_AR@50:95": -0.07356532356532355,
            "sam_mask_AR@50": 0.12362637362637363,
            "sam_mask_AR@75": -0.12545787545787546,
            "sam_mask_AR@95": -0.25,
            "sam_mask_AR@50:95": -0.08394383394383394
        },
        {
            "image_name": "RHA_00-45_500X07_png.rf.2e24ff0e093484de86e43a21ef7e62cb.jpg",
            "original_image_path": "/home/sprice/ICCV25/demo.v7i.coco/test/RHA_00-45_500X07_png.rf.2e24ff0e093484de86e43a21ef7e62cb.jpg",
            "gt_mask_path": "/home/sprice/ICCV25/demo.v7i.coco/test/annotations/RHA_00-45_500X07_png.rf.2e24ff0e093484de86e43a21ef7e62cb_mask.png",
            "processing_time_sec": 4.683362722396851,
            "base_box_AP@50": 1.0,
            "base_box_AP@75": 0.8910891089108911,
            "base_box_AP@95": 0.3407340734073407,
            "base_box_AP@50:95": 0.7439410607727439,
            "base_mask_AP@50": 0.9982398239823983,
            "base_mask_AP@75": 0.9982398239823983,
            "base_mask_AP@95": 0.47934793479347937,
            "base_mask_AP@50:95": 0.8252758609194254,
            "sam_box_AP@50": 0.2706270627062706,
            "sam_box_AP@75": 0.11522866572371522,
            "sam_box_AP@95": 0.007838283828382838,
            "sam_box_AP@50:95": 0.13123133741945622,
            "sam_mask_AP@50": 0.538953895389539,
            "sam_mask_AP@75": 0.4558389172250559,
            "sam_mask_AP@95": 0.30200770077007705,
            "sam_mask_AP@50:95": 0.4322668377948906,
            "base_box_AR@50": 0.5,
            "base_box_AR@75": 0.41964285714285715,
            "base_box_AR@95": 0.0875,
            "base_box_AR@50:95": 0.3357142857142857,
            "base_mask_AR@50": 0.5,
            "base_mask_AR@75": 0.5,
            "base_mask_AR@95": 0.13571428571428573,
            "base_mask_AR@50:95": 0.3785714285714286,
            "sam_box_AR@50": 0.04464285714285715,
            "sam_box_AR@75": -0.08392857142857142,
            "sam_box_AR@95": -0.20714285714285716,
            "sam_box_AR@50:95": -0.08214285714285714,
            "sam_mask_AR@50": 0.21607142857142858,
            "sam_mask_AR@75": 0.17321428571428574,
            "sam_mask_AR@95": 0.04464285714285715,
            "sam_mask_AR@50:95": 0.14464285714285716
        },
        {
            "image_name": "Rec-Cu-Ni-Powder_250x_7_SE_V1_png.rf.4c7c94e7a5f2b5ab0a942ce1b6f7193a.jpg",
            "original_image_path": "/home/sprice/ICCV25/demo.v7i.coco/test/Rec-Cu-Ni-Powder_250x_7_SE_V1_png.rf.4c7c94e7a5f2b5ab0a942ce1b6f7193a.jpg",
            "gt_mask_path": "/home/sprice/ICCV25/demo.v7i.coco/test/annotations/Rec-Cu-Ni-Powder_250x_7_SE_V1_png.rf.4c7c94e7a5f2b5ab0a942ce1b6f7193a_mask.png",
            "processing_time_sec": 35.52143692970276,
            "base_box_AP@50": 0.744833052566622,
            "base_box_AP@75": 0.42828413883187716,
            "base_box_AP@95": 0.00034855526368963427,
            "base_box_AP@50:95": 0.3911552488873963,
            "base_mask_AP@50": 0.6795760503684712,
            "base_mask_AP@75": 0.3531860870039446,
            "base_mask_AP@95": 0.0,
            "base_mask_AP@50:95": 0.34425404579080526,
            "sam_box_AP@50": 0.3109393081493506,
            "sam_box_AP@75": 0.16536953024182063,
            "sam_box_AP@95": 0.011234473662048935,
            "sam_box_AP@50:95": 0.1625144373510734,
            "sam_mask_AP@50": 0.3889558251216082,
            "sam_mask_AP@75": 0.19338406693972948,
            "sam_mask_AP@95": 0.013690740639998067,
            "sam_mask_AP@50:95": 0.19867687756711191,
            "base_box_AR@50": 0.8402364684954168,
            "base_box_AR@75": 0.5482700144653304,
            "base_box_AR@95": 0.011122819341997424,
            "base_box_AR@50:95": 0.46654310076758154,
            "base_mask_AR@50": 0.805286455087604,
            "base_mask_AR@75": 0.4721665137042954,
            "base_mask_AR@95": 0.0,
            "base_mask_AR@50:95": 0.42581765626396645,
            "sam_box_AR@50": 0.5230529400878495,
            "sam_box_AR@75": 0.34521907610727764,
            "sam_box_AR@95": 0.08722632010303244,
            "sam_box_AR@50:95": 0.31849944543271985,
            "sam_mask_AR@50": 0.5131887555661307,
            "sam_mask_AR@75": 0.29788760853718876,
            "sam_mask_AR@95": 0.05941927174803888,
            "sam_mask_AR@50:95": 0.2901652119504528
        },
        {
            "image_name": "Rec-Cu-Ni-Powder_250x_8_SE_V1_png.rf.cb5407549469443a93d2dc62dd52a6a1.jpg",
            "original_image_path": "/home/sprice/ICCV25/demo.v7i.coco/test/Rec-Cu-Ni-Powder_250x_8_SE_V1_png.rf.cb5407549469443a93d2dc62dd52a6a1.jpg",
            "gt_mask_path": "/home/sprice/ICCV25/demo.v7i.coco/test/annotations/Rec-Cu-Ni-Powder_250x_8_SE_V1_png.rf.cb5407549469443a93d2dc62dd52a6a1_mask.png",
            "processing_time_sec": 33.50348997116089,
            "base_box_AP@50": 0.780284166784497,
            "base_box_AP@75": 0.5351165033096237,
            "base_box_AP@95": 0.023180889517523177,
            "base_box_AP@50:95": 0.4461938532038813,
            "base_mask_AP@50": 0.6618385904097743,
            "base_mask_AP@75": 0.4645891142236349,
            "base_mask_AP@95": 0.0,
            "base_mask_AP@50:95": 0.37547590154446975,
            "sam_box_AP@50": 0.29374625728486076,
            "sam_box_AP@75": 0.07218602802294656,
            "sam_box_AP@95": 0.023394685154295835,
            "sam_box_AP@50:95": 0.12977565682070105,
            "sam_mask_AP@50": 0.36318290910718043,
            "sam_mask_AP@75": 0.20263674409320123,
            "sam_mask_AP@95": 0.03282765735583749,
            "sam_mask_AP@50:95": 0.19954910351873972,
            "base_box_AR@50": 0.8383341711700389,
            "base_box_AR@75": 0.6362734856101546,
            "base_box_AR@95": 0.04079152004524318,
            "base_box_AR@50:95": 0.5051330589418123,
            "base_mask_AR@50": 0.7759673086590424,
            "base_mask_AR@75": 0.5321191246701018,
            "base_mask_AR@95": 0.0,
            "base_mask_AR@50:95": 0.43602881110971475,
            "sam_box_AR@50": 0.4390300992836496,
            "sam_box_AR@75": 0.18939612919442,
            "sam_box_AR@95": 0.09301951112228227,
            "sam_box_AR@50:95": 0.24048191320011736,
            "sam_mask_AR@50": 0.46167093439738593,
            "sam_mask_AR@75": 0.2676220623350509,
            "sam_mask_AR@95": 0.06442833354279251,
            "sam_mask_AR@50:95": 0.26457377675840976
        },
        {
            "image_name": "Rec-Cu-Ni-Powder_250x_9_SE_png.rf.2b9d131a9fe115a2fb24f4512af0c9a6.jpg",
            "original_image_path": "/home/sprice/ICCV25/demo.v7i.coco/test/Rec-Cu-Ni-Powder_250x_9_SE_png.rf.2b9d131a9fe115a2fb24f4512af0c9a6.jpg",
            "gt_mask_path": "/home/sprice/ICCV25/demo.v7i.coco/test/annotations/Rec-Cu-Ni-Powder_250x_9_SE_png.rf.2b9d131a9fe115a2fb24f4512af0c9a6_mask.png",
            "processing_time_sec": 3.6183626651763916,
            "base_box_AP@50": 1.0,
            "base_box_AP@75": 0.5754950495049505,
            "base_box_AP@95": 0.19306930693069305,
            "base_box_AP@50:95": 0.5895214521452146,
            "base_mask_AP@50": 0.7301980198019802,
            "base_mask_AP@75": 0.5597434743474348,
            "base_mask_AP@95": 0.146039603960396,
            "base_mask_AP@50:95": 0.47866036603660367,
            "sam_box_AP@50": 0.5376727233162877,
            "sam_box_AP@75": 0.48146284408660645,
            "sam_box_AP@95": 0.2261315417256011,
            "sam_box_AP@50:95": 0.415089036376165,
            "sam_mask_AP@50": 0.509959924563885,
            "sam_mask_AP@75": 0.32278406412069777,
            "sam_mask_AP@95": 0.19625176803394623,
            "sam_mask_AP@50:95": 0.34299858557284296,
            "base_box_AR@50": 1.0,
            "base_box_AR@75": 0.5865384615384616,
            "base_box_AR@95": 0.18846153846153846,
            "base_box_AR@50:95": 0.5916666666666667,
            "base_mask_AR@50": 0.7307692307692308,
            "base_mask_AR@75": 0.5865384615384616,
            "base_mask_AR@95": 0.14423076923076922,
            "base_mask_AR@50:95": 0.4871794871794872,
            "sam_box_AR@50": 0.6461538461538461,
            "sam_box_AR@75": 0.601923076923077,
            "sam_box_AR@95": 0.33269230769230773,
            "sam_box_AR@50:95": 0.5269230769230769,
            "sam_mask_AR@50": 0.7788461538461539,
            "sam_mask_AR@75": 0.42115384615384616,
            "sam_mask_AR@95": 0.2326923076923077,
            "sam_mask_AR@50:95": 0.4775641025641026
        },
        {
            "image_name": "S01_03_SE1_500X11_png.rf.4b7fddca6f3354a728be814c4f62d5ae.jpg",
            "original_image_path": "/home/sprice/ICCV25/demo.v7i.coco/test/S01_03_SE1_500X11_png.rf.4b7fddca6f3354a728be814c4f62d5ae.jpg",
            "gt_mask_path": "/home/sprice/ICCV25/demo.v7i.coco/test/annotations/S01_03_SE1_500X11_png.rf.4b7fddca6f3354a728be814c4f62d5ae_mask.png",
            "processing_time_sec": 9.822195529937744,
            "base_box_AP@50": 0.954003672426066,
            "base_box_AP@75": 0.8407195131277834,
            "base_box_AP@95": 0.0925558654936701,
            "base_box_AP@50:95": 0.6290930170158399,
            "base_mask_AP@50": 0.954003672426066,
            "base_mask_AP@75": 0.8407195131277834,
            "base_mask_AP@95": 0.26828984590188343,
            "base_mask_AP@50:95": 0.6876710104852444,
            "sam_box_AP@50": 0.2877750835755741,
            "sam_box_AP@75": 0.16601825306359697,
            "sam_box_AP@95": 0.1447098494886915,
            "sam_box_AP@50:95": 0.19950106204262086,
            "sam_mask_AP@50": 0.7054519991688422,
            "sam_mask_AP@75": 0.38603608167834325,
            "sam_mask_AP@95": 0.16711006036501086,
            "sam_mask_AP@50:95": 0.4195327137373987,
            "base_box_AR@50": 0.47159090909090906,
            "base_box_AR@75": 0.41314935064935066,
            "base_box_AR@95": -0.1047077922077922,
            "base_box_AR@50:95": 0.26001082251082247,
            "base_mask_AR@50": 0.47159090909090906,
            "base_mask_AR@75": 0.41314935064935066,
            "base_mask_AR@95": -0.01623376623376624,
            "base_mask_AR@50:95": 0.2895021645021645,
            "sam_box_AR@50": 0.0689935064935065,
            "sam_box_AR@75": -0.008928571428571452,
            "sam_box_AR@95": -0.0478896103896104,
            "sam_box_AR@50:95": 0.0040584415584415485,
            "sam_mask_AR@50": 0.3474025974025974,
            "sam_mask_AR@75": 0.11688311688311688,
            "sam_mask_AR@95": -0.05681818181818184,
            "sam_mask_AR@50:95": 0.13582251082251082
        },
        {
            "image_name": "S02_01_SE1_1000X16_png.rf.1fab57db91783570e9210e6bcb342f81.jpg",
            "original_image_path": "/home/sprice/ICCV25/demo.v7i.coco/test/S02_01_SE1_1000X16_png.rf.1fab57db91783570e9210e6bcb342f81.jpg",
            "gt_mask_path": "/home/sprice/ICCV25/demo.v7i.coco/test/annotations/S02_01_SE1_1000X16_png.rf.1fab57db91783570e9210e6bcb342f81_mask.png",
            "processing_time_sec": 6.278728246688843,
            "base_box_AP@50": 0.9558393339333934,
            "base_box_AP@75": 0.9558393339333934,
            "base_box_AP@95": 0.1605021216407355,
            "base_box_AP@50:95": 0.6907269298358408,
            "base_mask_AP@50": 0.9558393339333934,
            "base_mask_AP@75": 0.8201614804337576,
            "base_mask_AP@95": 0.19102722772277228,
            "base_mask_AP@50:95": 0.6556760140299746,
            "sam_box_AP@50": 0.2769429762525124,
            "sam_box_AP@75": 0.01587615745380206,
            "sam_box_AP@95": 0.0015307451797811362,
            "sam_box_AP@50:95": 0.09811662629536522,
            "sam_mask_AP@50": 0.39483659904451984,
            "sam_mask_AP@75": 0.2452145214521452,
            "sam_mask_AP@95": 0.11894040365575019,
            "sam_mask_AP@50:95": 0.2529971747174718,
            "base_box_AR@50": 1.0,
            "base_box_AR@75": 1.0,
            "base_box_AR@95": 0.22023809523809523,
            "base_box_AR@50:95": 0.7400793650793651,
            "base_mask_AR@50": 1.0,
            "base_mask_AR@75": 0.8630952380952381,
            "base_mask_AR@95": 0.24776785714285715,
            "base_mask_AR@50:95": 0.7036210317460317,
            "sam_box_AR@50": 0.3430059523809524,
            "sam_box_AR@75": 0.08258928571428571,
            "sam_box_AR@95": 0.027529761904761904,
            "sam_box_AR@50:95": 0.15104166666666666,
            "sam_mask_AR@50": 0.6302083333333333,
            "sam_mask_AR@75": 0.47991071428571425,
            "sam_mask_AR@95": 0.19270833333333331,
            "sam_mask_AR@50:95": 0.43427579365079355
        },
        {
            "image_name": "S02_02_SE1_300X18_png.rf.1a16e8c5f4e008cb2fc48c98b35778fb.jpg",
            "original_image_path": "/home/sprice/ICCV25/demo.v7i.coco/test/S02_02_SE1_300X18_png.rf.1a16e8c5f4e008cb2fc48c98b35778fb.jpg",
            "gt_mask_path": "/home/sprice/ICCV25/demo.v7i.coco/test/annotations/S02_02_SE1_300X18_png.rf.1a16e8c5f4e008cb2fc48c98b35778fb_mask.png",
            "processing_time_sec": 37.313987016677856,
            "base_box_AP@50": null,
            "base_box_AP@75": null,
            "base_box_AP@95": null,
            "base_box_AP@50:95": null,
            "base_mask_AP@50": null,
            "base_mask_AP@75": null,
            "base_mask_AP@95": null,
            "base_mask_AP@50:95": null,
            "sam_box_AP@50": null,
            "sam_box_AP@75": null,
            "sam_box_AP@95": null,
            "sam_box_AP@50:95": null,
            "sam_mask_AP@50": null,
            "sam_mask_AP@75": null,
            "sam_mask_AP@95": null,
            "sam_mask_AP@50:95": null,
            "base_box_AR@50": null,
            "base_box_AR@75": null,
            "base_box_AR@95": null,
            "base_box_AR@50:95": null,
            "base_mask_AR@50": null,
            "base_mask_AR@75": null,
            "base_mask_AR@95": null,
            "base_mask_AR@50:95": null,
            "sam_box_AR@50": null,
            "sam_box_AR@75": null,
            "sam_box_AR@95": null,
            "sam_box_AR@50:95": null,
            "sam_mask_AR@50": null,
            "sam_mask_AR@75": null,
            "sam_mask_AR@95": null,
            "sam_mask_AR@50:95": null
        },
        {
            "image_name": "S02_03_SE1_1000X24_png.rf.61ceee7fe0a4f4ccabd61c1e71524baf.jpg",
            "original_image_path": "/home/sprice/ICCV25/demo.v7i.coco/test/S02_03_SE1_1000X24_png.rf.61ceee7fe0a4f4ccabd61c1e71524baf.jpg",
            "gt_mask_path": "/home/sprice/ICCV25/demo.v7i.coco/test/annotations/S02_03_SE1_1000X24_png.rf.61ceee7fe0a4f4ccabd61c1e71524baf_mask.png",
            "processing_time_sec": 8.033015012741089,
            "base_box_AP@50": null,
            "base_box_AP@75": null,
            "base_box_AP@95": null,
            "base_box_AP@50:95": null,
            "base_mask_AP@50": null,
            "base_mask_AP@75": null,
            "base_mask_AP@95": null,
            "base_mask_AP@50:95": null,
            "sam_box_AP@50": null,
            "sam_box_AP@75": null,
            "sam_box_AP@95": null,
            "sam_box_AP@50:95": null,
            "sam_mask_AP@50": null,
            "sam_mask_AP@75": null,
            "sam_mask_AP@95": null,
            "sam_mask_AP@50:95": null,
            "base_box_AR@50": null,
            "base_box_AR@75": null,
            "base_box_AR@95": null,
            "base_box_AR@50:95": null,
            "base_mask_AR@50": null,
            "base_mask_AR@75": null,
            "base_mask_AR@95": null,
            "base_mask_AR@50:95": null,
            "sam_box_AR@50": null,
            "sam_box_AR@75": null,
            "sam_box_AR@95": null,
            "sam_box_AR@50:95": null,
            "sam_mask_AR@50": null,
            "sam_mask_AR@75": null,
            "sam_mask_AR@95": null,
            "sam_mask_AR@50:95": null
        },
        {
            "image_name": "S04_01_SE1_1000X45_png.rf.baa89207016e4da58f6ec0ab4f2b008f.jpg",
            "original_image_path": "/home/sprice/ICCV25/demo.v7i.coco/test/S04_01_SE1_1000X45_png.rf.baa89207016e4da58f6ec0ab4f2b008f.jpg",
            "gt_mask_path": "/home/sprice/ICCV25/demo.v7i.coco/test/annotations/S04_01_SE1_1000X45_png.rf.baa89207016e4da58f6ec0ab4f2b008f_mask.png",
            "processing_time_sec": 30.768941164016724,
            "base_box_AP@50": 0.8632374859198603,
            "base_box_AP@75": 0.6979289035905055,
            "base_box_AP@95": 0.0023398138133141045,
            "base_box_AP@50:95": 0.5211687344412267,
            "base_mask_AP@50": 0.8181762714691562,
            "base_mask_AP@75": 0.6421659203245486,
            "base_mask_AP@95": 0.0,
            "base_mask_AP@50:95": 0.48678073059790156,
            "sam_box_AP@50": 0.2921700538995309,
            "sam_box_AP@75": 0.14943994422872603,
            "sam_box_AP@95": 0.031233862711288987,
            "sam_box_AP@50:95": 0.15761462027984863,
            "sam_mask_AP@50": 0.35430001828086455,
            "sam_mask_AP@75": 0.25627301039073724,
            "sam_mask_AP@95": 0.10370772059613557,
            "sam_mask_AP@50:95": 0.2380935830892458,
            "base_box_AR@50": 0.9078947368421053,
            "base_box_AR@75": 0.7395334928229665,
            "base_box_AR@95": 0.02516945773524721,
            "base_box_AR@50:95": 0.557532562466773,
            "base_mask_AR@50": 0.8748006379585327,
            "base_mask_AR@75": 0.6583290612895876,
            "base_mask_AR@95": 0.0,
            "base_mask_AR@50:95": 0.5110432330827067,
            "sam_box_AR@50": 0.4276885395306448,
            "sam_box_AR@75": 0.29714912280701755,
            "sam_box_AR@95": 0.13548786739576213,
            "sam_box_AR@50:95": 0.28677517657780816,
            "sam_mask_AR@50": 0.4751367053998633,
            "sam_mask_AR@75": 0.37957820688083843,
            "sam_mask_AR@95": 0.16057188425609478,
            "sam_mask_AR@50:95": 0.33842893217893216
        },
        {
            "image_name": "S05_02_SE1_300X59_png.rf.ab223b36432318e07ad4d0e7c1d7dea6.jpg",
            "original_image_path": "/home/sprice/ICCV25/demo.v7i.coco/test/S05_02_SE1_300X59_png.rf.ab223b36432318e07ad4d0e7c1d7dea6.jpg",
            "gt_mask_path": "/home/sprice/ICCV25/demo.v7i.coco/test/annotations/S05_02_SE1_300X59_png.rf.ab223b36432318e07ad4d0e7c1d7dea6_mask.png",
            "processing_time_sec": 24.43088412284851,
            "base_box_AP@50": 0.8310859299941129,
            "base_box_AP@75": 0.6398600618979469,
            "base_box_AP@95": 0.0020668623590862963,
            "base_box_AP@50:95": 0.491004284750382,
            "base_mask_AP@50": 0.8307020552281491,
            "base_mask_AP@75": 0.6377132729985703,
            "base_mask_AP@95": 0.0,
            "base_mask_AP@50:95": 0.48947177607557313,
            "sam_box_AP@50": 0.2669381551627613,
            "sam_box_AP@75": 0.13867272386672902,
            "sam_box_AP@95": 0.04239358946493091,
            "sam_box_AP@50:95": 0.14933482283147373,
            "sam_mask_AP@50": 0.5455747622682839,
            "sam_mask_AP@75": 0.3845600709532382,
            "sam_mask_AP@95": 0.18764364486646856,
            "sam_mask_AP@50:95": 0.3725928260293302,
            "base_box_AR@50": 0.8573707970112079,
            "base_box_AR@75": 0.6868384184308842,
            "base_box_AR@95": 0.018796699875466998,
            "base_box_AR@50:95": 0.5210019717725197,
            "base_mask_AR@50": 0.8573707970112079,
            "base_mask_AR@75": 0.6652630759651308,
            "base_mask_AR@95": 0.0,
            "base_mask_AR@50:95": 0.5075446243254462,
            "sam_box_AR@50": 0.43343711083437114,
            "sam_box_AR@75": 0.2991438356164383,
            "sam_box_AR@95": 0.18086861768368617,
            "sam_box_AR@50:95": 0.3044831880448319,
            "sam_mask_AR@50": 0.6923334371108344,
            "sam_mask_AR@75": 0.5579778953922789,
            "sam_mask_AR@95": 0.255222602739726,
            "sam_mask_AR@50:95": 0.5018446450809464
        },
        {
            "image_name": "S05_03_SE1_1000X65_png.rf.b1b275b60d329ab4fae1100a32dcfd4e.jpg",
            "original_image_path": "/home/sprice/ICCV25/demo.v7i.coco/test/S05_03_SE1_1000X65_png.rf.b1b275b60d329ab4fae1100a32dcfd4e.jpg",
            "gt_mask_path": "/home/sprice/ICCV25/demo.v7i.coco/test/annotations/S05_03_SE1_1000X65_png.rf.b1b275b60d329ab4fae1100a32dcfd4e_mask.png",
            "processing_time_sec": 3.5310933589935303,
            "base_box_AP@50": 1.0,
            "base_box_AP@75": 1.0,
            "base_box_AP@95": 0.17557755775577555,
            "base_box_AP@50:95": 0.7251925192519253,
            "base_mask_AP@50": 1.0,
            "base_mask_AP@75": 1.0,
            "base_mask_AP@95": 0.1353135313531353,
            "base_mask_AP@50:95": 0.7117711771177118,
            "sam_box_AP@50": 0.3800880088008801,
            "sam_box_AP@75": 0.0539053905390539,
            "sam_box_AP@95": 0.0,
            "sam_box_AP@50:95": 0.14466446644664466,
            "sam_mask_AP@50": 0.2531824611032532,
            "sam_mask_AP@75": 0.11324846770391324,
            "sam_mask_AP@95": 0.07562470532767562,
            "sam_mask_AP@50:95": 0.14735187804494737,
            "base_box_AR@50": 0.5,
            "base_box_AR@75": 0.5,
            "base_box_AR@95": -0.07291666666666669,
            "base_box_AR@50:95": 0.30902777777777773,
            "base_mask_AR@50": 0.5,
            "base_mask_AR@75": 0.5,
            "base_mask_AR@95": -0.13194444444444445,
            "base_mask_AR@50:95": 0.28935185185185186,
            "sam_box_AR@50": 0.045138888888888895,
            "sam_box_AR@75": -0.13194444444444445,
            "sam_box_AR@95": -0.25,
            "sam_box_AR@50:95": -0.11226851851851853,
            "sam_mask_AR@50": 0.045138888888888895,
            "sam_mask_AR@75": -0.07291666666666669,
            "sam_mask_AR@95": -0.13194444444444445,
            "sam_mask_AR@50:95": -0.05324074074074075
        },
        {
            "image_name": "S07_03_SE1_1250X92_png.rf.03fe49af01d0314c26c63cbf31c6f316.jpg",
            "original_image_path": "/home/sprice/ICCV25/demo.v7i.coco/test/S07_03_SE1_1250X92_png.rf.03fe49af01d0314c26c63cbf31c6f316.jpg",
            "gt_mask_path": "/home/sprice/ICCV25/demo.v7i.coco/test/annotations/S07_03_SE1_1250X92_png.rf.03fe49af01d0314c26c63cbf31c6f316_mask.png",
            "processing_time_sec": 4.644315958023071,
            "base_box_AP@50": 0.7558803499397558,
            "base_box_AP@75": 0.5763560971481763,
            "base_box_AP@95": 0.047524752475247525,
            "base_box_AP@50:95": 0.45992039985439326,
            "base_mask_AP@50": 0.7558803499397558,
            "base_mask_AP@75": 0.6306846069222307,
            "base_mask_AP@95": 0.0891089108910891,
            "base_mask_AP@50:95": 0.4918912892510252,
            "sam_box_AP@50": 0.36820275434136823,
            "sam_box_AP@75": 0.176017601760176,
            "sam_box_AP@95": 0.05800964711855801,
            "sam_box_AP@50:95": 0.20074333440670075,
            "sam_mask_AP@50": 0.44444444444444453,
            "sam_mask_AP@75": 0.31903190319031904,
            "sam_mask_AP@95": 0.00847084708470847,
            "sam_mask_AP@50:95": 0.25731573157315735,
            "base_box_AR@50": 0.5,
            "base_box_AR@75": 0.3693181818181818,
            "base_box_AR@95": -0.1628787878787879,
            "base_box_AR@50:95": 0.23547979797979798,
            "base_mask_AR@50": 0.5,
            "base_mask_AR@75": 0.4128787878787879,
            "base_mask_AR@95": -0.11931818181818182,
            "base_mask_AR@50:95": 0.26452020202020204,
            "sam_box_AR@50": 0.09848484848484848,
            "sam_box_AR@75": -0.03219696969696968,
            "sam_box_AR@95": -0.11931818181818182,
            "sam_box_AR@50:95": -0.01767676767676768,
            "sam_mask_AR@50": 0.14204545454545456,
            "sam_mask_AR@75": 0.05492424242424243,
            "sam_mask_AR@95": -0.20643939393939392,
            "sam_mask_AR@50:95": -0.003156565656565647
        },
        {
            "image_name": "Sc1Tile_001-002-000_0-000_png.rf.05bb96317364c2a84f4eb06582dde5e9.jpg",
            "original_image_path": "/home/sprice/ICCV25/demo.v7i.coco/test/Sc1Tile_001-002-000_0-000_png.rf.05bb96317364c2a84f4eb06582dde5e9.jpg",
            "gt_mask_path": "/home/sprice/ICCV25/demo.v7i.coco/test/annotations/Sc1Tile_001-002-000_0-000_png.rf.05bb96317364c2a84f4eb06582dde5e9_mask.png",
            "processing_time_sec": 83.47428560256958,
            "base_box_AP@50": 0.7426279808279003,
            "base_box_AP@75": 0.4911790066754751,
            "base_box_AP@95": 0.008785164230708783,
            "base_box_AP@50:95": 0.41419738391136135,
            "base_mask_AP@50": 0.7020614861126476,
            "base_mask_AP@75": 0.45365933496292205,
            "base_mask_AP@95": 0.0008532904572508533,
            "base_mask_AP@50:95": 0.3855247038442735,
            "sam_box_AP@50": 0.24680705191379126,
            "sam_box_AP@75": 0.11514761390565321,
            "sam_box_AP@95": 0.016377240479179003,
            "sam_box_AP@50:95": 0.12611063543287448,
            "sam_mask_AP@50": 0.31571837465150504,
            "sam_mask_AP@75": 0.10734513037537195,
            "sam_mask_AP@95": 0.00252961872541934,
            "sam_mask_AP@50:95": 0.14186437458409878,
            "base_box_AR@50": 0.7749861930896413,
            "base_box_AR@75": 0.5446104260759433,
            "base_box_AR@95": 0.04666470183711563,
            "base_box_AR@50:95": 0.45542044033423346,
            "base_mask_AR@50": 0.7451521481693896,
            "base_mask_AR@75": 0.4894999442413236,
            "base_mask_AR@95": 0.009332940367423126,
            "base_mask_AR@50:95": 0.4146616775927121,
            "sam_box_AR@50": 0.36569576871301007,
            "sam_box_AR@75": 0.21780882341227167,
            "sam_box_AR@95": 0.04748315955212507,
            "sam_box_AR@50:95": 0.21032925055913562,
            "sam_mask_AR@50": 0.4495622943898806,
            "sam_mask_AR@75": 0.21774028670580395,
            "sam_mask_AR@95": 0.028271640340605857,
            "sam_mask_AR@50:95": 0.23185807381209686
        },
        {
            "image_name": "TruForm174-2_00-37_500X16_png.rf.17ddf81ab4dd63c5ce6f66654a48c5b4.jpg",
            "original_image_path": "/home/sprice/ICCV25/demo.v7i.coco/test/TruForm174-2_00-37_500X16_png.rf.17ddf81ab4dd63c5ce6f66654a48c5b4.jpg",
            "gt_mask_path": "/home/sprice/ICCV25/demo.v7i.coco/test/annotations/TruForm174-2_00-37_500X16_png.rf.17ddf81ab4dd63c5ce6f66654a48c5b4_mask.png",
            "processing_time_sec": 19.855767726898193,
            "base_box_AP@50": 0.908079876955411,
            "base_box_AP@75": 0.7941771602369099,
            "base_box_AP@95": 0.02813708495949835,
            "base_box_AP@50:95": 0.576798040717273,
            "base_mask_AP@50": 0.8069212044868708,
            "base_mask_AP@75": 0.7106550312043086,
            "base_mask_AP@95": 0.0,
            "base_mask_AP@50:95": 0.5058587452303931,
            "sam_box_AP@50": 0.24686533532617533,
            "sam_box_AP@75": 0.1499244933529368,
            "sam_box_AP@95": 0.085797060591371,
            "sam_box_AP@50:95": 0.1608622964234944,
            "sam_mask_AP@50": 0.3394563392704574,
            "sam_mask_AP@75": 0.15242822402541006,
            "sam_mask_AP@95": 0.04577363020059344,
            "sam_mask_AP@50:95": 0.17921939783215363,
            "base_box_AR@50": 0.9129353233830846,
            "base_box_AR@75": 0.7999707345624817,
            "base_box_AR@95": 0.08909074536818172,
            "base_box_AR@50:95": 0.6006656011045827,
            "base_mask_AR@50": 0.9129353233830846,
            "base_mask_AR@75": 0.7129060579455663,
            "base_mask_AR@95": 0.0,
            "base_mask_AR@50:95": 0.5419471271095503,
            "sam_box_AR@50": 0.33633866864771167,
            "sam_box_AR@75": 0.2213480110758425,
            "sam_box_AR@95": 0.1408905697755566,
            "sam_box_AR@50:95": 0.23285908316637027,
            "sam_mask_AR@50": 0.5527228112829516,
            "sam_mask_AR@75": 0.29610994799756873,
            "sam_mask_AR@95": 0.1408905697755566,
            "sam_mask_AR@50:95": 0.3299077763520257
        }
    ],
    "average_metrics": {
        "base_box_AP@50": 0.8748068672607067,
        "base_box_AP@75": 0.7047131087610918,
        "base_box_AP@95": 0.09764345099588041,
        "base_box_AP@50:95": 0.5590544756725597,
        "base_mask_AP@50": 0.8317887435762114,
        "base_mask_AP@75": 0.6605639838296353,
        "base_mask_AP@95": 0.08110390744882813,
        "base_mask_AP@50:95": 0.5244855449515584,
        "sam_box_AP@50": 0.323808663734913,
        "sam_box_AP@75": 0.15900872097725727,
        "sam_box_AP@95": 0.05738125080196425,
        "sam_box_AP@50:95": 0.18006621183804483,
        "sam_mask_AP@50": 0.417799306754983,
        "sam_mask_AP@75": 0.23179044301326712,
        "sam_mask_AP@95": 0.08918392541750848,
        "sam_mask_AP@50:95": 0.24625789172858623,
        "base_box_AR@50": 0.7271829661019815,
        "base_box_AR@75": 0.5815264069254206,
        "base_box_AR@95": 0.020339007546658648,
        "base_box_AR@50:95": 0.4430161268580202,
        "base_mask_AR@50": 0.6997432111913189,
        "base_mask_AR@75": 0.5312781033592509,
        "base_mask_AR@95": -0.015713207565458524,
        "base_mask_AR@50:95": 0.4051027023283704,
        "sam_box_AR@50": 0.3042634188331847,
        "sam_box_AR@75": 0.1521664070327119,
        "sam_box_AR@95": 0.01800071000318462,
        "sam_box_AR@50:95": 0.15814351195636037,
        "sam_mask_AR@50": 0.4064712040867573,
        "sam_mask_AR@75": 0.22184037388986963,
        "sam_mask_AR@95": 0.027678199621726223,
        "sam_mask_AR@50:95": 0.21866325919945107
    }
}